{
    "execution_plan": [
        {
            "id": 1,
            "description": "Find product IDs that have been ordered at least twice (appear in Order_Items two or more times).",
            "database": "mysql+pymysql://appuser:apppass@localhost:3308/orders_db",
            "query": "SELECT product_id FROM Order_Items GROUP BY product_id HAVING COUNT(*) >= 2;",
            "depends_on": [],
            "join_info": null
        },
        {
            "id": 2,
            "description": "Select id, name, price and color for products that are NOT in the set of frequently ordered products from step 1 (i.e., products ordered fewer than twice, including never ordered).",
            "database": "mysql+pymysql://appuser:apppass@localhost:3307/products_db",
            "query": "SELECT product_id, product_name, product_price, product_color FROM Products WHERE product_id NOT IN ($step1.product_id);",
            "depends_on": [
                1
            ],
            "join_info": {
                "type": "LEFT",
                "on": {
                    "current_step_column": "product_id",
                    "dependency_step_column": "product_id"
                }
            }
        }
    ],
    "final_output_columns": [
        "product_id",
        "product_name",
        "product_price",
        "product_color"
    ],
    "final_aggregation": {
        "type": "NONE",
        "column": ""
    }
}